Sequence/Arithmetic.py
Sequence/Geometric.py
Sequence/__init__.py
formulas/__init__.py
formulas/analytic_geometry.py
formulas/arithmetic_progression.py
formulas/basic_math.py
formulas/calculus.py
formulas/circle.py
formulas/cleanup.py
formulas/equation.py
formulas/geometric_progression.py
formulas/linear_algebra.py
formulas/polygon.py
formulas/quadrilateral.py
formulas/solid_3d.py
formulas/triangle.py
formulas/trigonometry.py
naesungmath-3.1.0.dist-info/licenses/LICENSE
naesungmath-3.1.0.dist-info/METADATA
naesungmath-3.1.0.dist-info/WHEEL
naesungmath-3.1.0.dist-info/top_level.txt
naesungmath-3.1.0.dist-info/RECORD
