Metadata-Version: 2.4
Name: naesungmath
Version: 3.1.0
Summary: Science is Magic! Let's memorize spells <Math Formula>
Author-email: Choi Minseo <minseo0388@daum.net>
Classifier: Programming Language :: Python :: 3
Classifier: License :: OSI Approved :: GNU General Public License v3 (GPLv3)
Classifier: Operating System :: OS Independent
Requires-Python: >=3.6
License-File: LICENSE
Dynamic: license-file
